odoo/addons/connector_importer_demo/README.rst
odoo/addons/connector_importer_demo/__init__.py
odoo/addons/connector_importer_demo/__manifest__.py
odoo/addons/connector_importer_demo/hooks.py
odoo/addons/connector_importer_demo/data/import_backend.xml
odoo/addons/connector_importer_demo/data/import_recordset.xml
odoo/addons/connector_importer_demo/data/import_source.xml
odoo/addons/connector_importer_demo/data/import_type.xml
odoo/addons/connector_importer_demo/example/res.partner.csv
odoo/addons/connector_importer_demo/i18n/connector_importer_demo.pot
odoo/addons/connector_importer_demo/i18n/it.po
odoo/addons/connector_importer_demo/readme/DESCRIPTION.rst
odoo/addons/connector_importer_demo/static/description/icon.png
odoo/addons/connector_importer_demo/static/description/index.html
odoo14_addon_connector_importer_demo-14.0.1.0.1.dev4.dist-info/METADATA
odoo14_addon_connector_importer_demo-14.0.1.0.1.dev4.dist-info/WHEEL
odoo14_addon_connector_importer_demo-14.0.1.0.1.dev4.dist-info/top_level.txt
odoo14_addon_connector_importer_demo-14.0.1.0.1.dev4.dist-info/RECORD
